{"basics":{"name":"Bhanu Pratyush Mantha","label":"Bachelor's Student at National Institute of Technology, Tiruchirappalli","image":"","email":"pratyushmantha.w@gmail.com","url":"https://pratyush-1.github.io","location":{"postalCode":"CA 94305","city":"Stanford","countryCode":"US","region":"California"}},"volunteer":[],"education":[{"institution":"National Institute of Technology, Tiruchirappalli","url":"https://www.nitt.edu/","area":"Electronics and Communication Engineering","studyType":"Bachelor of Technology","startDate":"2021","endDate":"2025","score":""}],"languages":[{"language":"English","fluency":"Fluent"},{"language":"Hindi","fluency":"Fluent"},{"language":"Telugu","fluency":"Fluent"},{"language":"Tamil","fluency":"Intermediate"}],"interests":[],"references":[],"projects":[]}